dsputility/__init__.py
dsputility/dbintf/__init__.py
dsputility/dbintf/dbintf.py
dsputility/log/__init__.py
dsputility/log/log.py
dsputility/log/test_log.py
DSPutility-0.0.21.dist-info/LICENSE.txt
DSPutility-0.0.21.dist-info/METADATA
DSPutility-0.0.21.dist-info/WHEEL
DSPutility-0.0.21.dist-info/top_level.txt
DSPutility-0.0.21.dist-info/RECORD
