Metadata-Version: 2.1
Name: DSPutility
Version: 0.0.21
Summary: DSP utility collection
Home-page: https://github.com/dspim/DSPutility
Author: bonzo
Author-email: bonzo.yang@dsp.im
License: UNKNOWN
Platform: UNKNOWN
Classifier: Programming Language :: Python :: 3
Classifier: License :: OSI Approved :: MIT License
Classifier: Operating System :: OS Independent
Requires-Python: >=3.8
License-File: LICENSE.txt
Requires-Dist: sqlalchemy
Requires-Dist: sqlalchemy-utils
